remove_bg_python/__init__.py
remove_bg_python/remove.py
remove_bg_python-1.0.0.dist-info/LICENSE.txt
remove_bg_python-1.0.0.dist-info/METADATA
remove_bg_python-1.0.0.dist-info/WHEEL
remove_bg_python-1.0.0.dist-info/top_level.txt
remove_bg_python-1.0.0.dist-info/RECORD
